[
{"name":"runClasspath.super.mill.scalalib.RunModule.runClasspath","cat":"job","ph":"X","ts":95064441,"dur":53659,"pid":1,"tid":0,"args":["cached"]},
{"name":"scriptSources","cat":"job","ph":"X","ts":95129793,"dur":69736,"pid":1,"tid":0,"args":[]},
{"name":"parseBuildFiles","cat":"job","ph":"X","ts":95201686,"dur":17685,"pid":1,"tid":0,"args":["cached"]},
{"name":"cliImports","cat":"job","ph":"X","ts":95220199,"dur":6280,"pid":1,"tid":0,"args":[]},
{"name":"runIvyDeps","cat":"job","ph":"X","ts":95227096,"dur":2256,"pid":1,"tid":0,"args":["cached"]},
{"name":"scalaVersion","cat":"job","ph":"X","ts":95229975,"dur":2303,"pid":1,"tid":0,"args":["cached"]},
{"name":"platformSuffix","cat":"job","ph":"X","ts":95232913,"dur":1911,"pid":1,"tid":0,"args":["cached"]},
{"name":"ivyDeps","cat":"job","ph":"X","ts":95235355,"dur":70186,"pid":1,"tid":0,"args":["cached"]},
{"name":"mandatoryIvyDeps.super.mill.scalalib.JavaModule.mandatoryIvyDeps","cat":"job","ph":"X","ts":95306262,"dur":4141,"pid":1,"tid":0,"args":["cached"]},
{"name":"scalaOrganization","cat":"job","ph":"X","ts":95311079,"dur":2421,"pid":1,"tid":0,"args":["cached"]},
{"name":"scalaLibraryIvyDeps","cat":"job","ph":"X","ts":95314297,"dur":2751,"pid":1,"tid":0,"args":["cached"]},
{"name":"mandatoryIvyDeps","cat":"job","ph":"X","ts":95317755,"dur":2563,"pid":1,"tid":0,"args":["cached"]},
{"name":"transitiveIvyDeps","cat":"job","ph":"X","ts":95321505,"dur":2956,"pid":1,"tid":0,"args":["cached"]},
{"name":"resolveDepsExclusions","cat":"job","ph":"X","ts":95325326,"dur":5646,"pid":1,"tid":0,"args":["cached"]},
{"name":"resolvedRunIvyDeps","cat":"job","ph":"X","ts":95332456,"dur":3913,"pid":1,"tid":0,"args":["cached"]},
{"name":"transitiveLocalClasspath","cat":"job","ph":"X","ts":95337037,"dur":1981,"pid":1,"tid":0,"args":["cached"]},
{"name":"compileResources","cat":"job","ph":"X","ts":95339489,"dur":5048,"pid":1,"tid":0,"args":[]},
{"name":"enclosingClasspath","cat":"job","ph":"X","ts":95345099,"dur":3286,"pid":1,"tid":0,"args":[]},
{"name":"lineNumberPluginClasspath","cat":"job","ph":"X","ts":95348866,"dur":9649,"pid":1,"tid":0,"args":["cached"]},
{"name":"unmanagedClasspath","cat":"job","ph":"X","ts":95359449,"dur":8863,"pid":1,"tid":0,"args":["cached"]},
{"name":"localCompileClasspath","cat":"job","ph":"X","ts":95369692,"dur":5683,"pid":1,"tid":0,"args":["cached"]},
{"name":"localRunClasspath.super.mill.scalalib.RunModule.localRunClasspath","cat":"job","ph":"X","ts":95376065,"dur":2017,"pid":1,"tid":0,"args":["cached"]},
{"name":"resources.super.mill.scalalib.JavaModule.resources","cat":"job","ph":"X","ts":95378558,"dur":4620,"pid":1,"tid":0,"args":[]},
{"name":"resources","cat":"job","ph":"X","ts":95383884,"dur":1357,"pid":1,"tid":0,"args":["cached"]},
{"name":"mill.scalalib.ZincWorkerModule.classpath","cat":"job","ph":"X","ts":95386182,"dur":48406,"pid":1,"tid":0,"args":["cached"]},
{"name":"mill.scalalib.ZincWorkerModule.zincLogDebug","cat":"job","ph":"X","ts":95435148,"dur":2544,"pid":1,"tid":0,"args":[]},
{"name":"mill.scalalib.ZincWorkerModule.worker","cat":"job","ph":"X","ts":95438134,"dur":221958,"pid":1,"tid":0,"args":[]},
{"name":"upstreamCompileOutput","cat":"job","ph":"X","ts":95660638,"dur":1543,"pid":1,"tid":0,"args":["cached"]},
{"name":"sources.super.mill.scalalib.JavaModule.sources","cat":"job","ph":"X","ts":95662652,"dur":3797,"pid":1,"tid":0,"args":[]},
{"name":"sources","cat":"job","ph":"X","ts":95666968,"dur":1444,"pid":1,"tid":0,"args":["cached"]},
{"name":"generateScriptSources","cat":"job","ph":"X","ts":95668953,"dur":1765,"pid":1,"tid":0,"args":["cached"]},
{"name":"generatedSources","cat":"job","ph":"X","ts":95672917,"dur":1597,"pid":1,"tid":0,"args":["cached"]},
{"name":"allSources","cat":"job","ph":"X","ts":95675019,"dur":1382,"pid":1,"tid":0,"args":["cached"]},
{"name":"allSourceFiles","cat":"job","ph":"X","ts":95676842,"dur":1208,"pid":1,"tid":0,"args":["cached"]},
{"name":"compileIvyDeps","cat":"job","ph":"X","ts":95678386,"dur":1188,"pid":1,"tid":0,"args":["cached"]},
{"name":"transitiveCompileIvyDeps","cat":"job","ph":"X","ts":95679952,"dur":1474,"pid":1,"tid":0,"args":["cached"]},
{"name":"resolvedIvyDeps","cat":"job","ph":"X","ts":95681938,"dur":2690,"pid":1,"tid":0,"args":["cached"]},
{"name":"transitiveCompileClasspath","cat":"job","ph":"X","ts":95685630,"dur":3309,"pid":1,"tid":0,"args":["cached"]},
{"name":"compileClasspath","cat":"job","ph":"X","ts":95689497,"dur":3738,"pid":1,"tid":0,"args":["cached"]},
{"name":"javacOptions","cat":"job","ph":"X","ts":95693618,"dur":1605,"pid":1,"tid":0,"args":["cached"]},
{"name":"mandatoryScalacOptions","cat":"job","ph":"X","ts":95695654,"dur":1569,"pid":1,"tid":0,"args":["cached"]},
{"name":"scalacPluginIvyDeps","cat":"job","ph":"X","ts":95697631,"dur":2632,"pid":1,"tid":0,"args":["cached"]},
{"name":"enablePluginScalacOptions.super.mill.scalalib.ScalaModule.enablePluginScalacOptions","cat":"job","ph":"X","ts":95700671,"dur":2377,"pid":1,"tid":0,"args":["cached"]},
{"name":"scalacOptions.super.mill.scalalib.ScalaModule.scalacOptions","cat":"job","ph":"X","ts":95703716,"dur":2255,"pid":1,"tid":0,"args":["cached"]},
{"name":"scalacOptions","cat":"job","ph":"X","ts":95706358,"dur":1470,"pid":1,"tid":0,"args":["cached"]},
{"name":"allScalacOptions","cat":"job","ph":"X","ts":95708556,"dur":1623,"pid":1,"tid":0,"args":["cached"]},
{"name":"scalaCompilerClasspath","cat":"job","ph":"X","ts":95710578,"dur":2177,"pid":1,"tid":0,"args":["cached"]},
{"name":"scalacPluginClasspath.super.mill.scalalib.ScalaModule.scalacPluginClasspath","cat":"job","ph":"X","ts":95713250,"dur":2909,"pid":1,"tid":0,"args":["cached"]},
{"name":"scalacPluginClasspath","cat":"job","ph":"X","ts":95716739,"dur":3907,"pid":1,"tid":0,"args":["cached"]},
{"name":"zincReportCachedProblems","cat":"job","ph":"X","ts":95721324,"dur":3078,"pid":1,"tid":0,"args":[]},
{"name":"zincIncrementalCompilation","cat":"job","ph":"X","ts":95724654,"dur":1528,"pid":1,"tid":0,"args":["cached"]},
{"name":"zincAuxiliaryClassFileExtensions.super.mill.scalalib.JavaModule.zincAuxiliaryClassFileExtensions","cat":"job","ph":"X","ts":95726482,"dur":1485,"pid":1,"tid":0,"args":["cached"]},
{"name":"zincAuxiliaryClassFileExtensions","cat":"job","ph":"X","ts":95728320,"dur":1659,"pid":1,"tid":0,"args":["cached"]},
{"name":"compile","cat":"job","ph":"X","ts":95730562,"dur":1846,"pid":1,"tid":0,"args":["cached"]},
{"name":"localRunClasspath","cat":"job","ph":"X","ts":95732911,"dur":1352,"pid":1,"tid":0,"args":["cached"]},
{"name":"localClasspath","cat":"job","ph":"X","ts":95734652,"dur":3842,"pid":1,"tid":0,"args":["cached"]},
{"name":"runClasspath","cat":"job","ph":"X","ts":95738940,"dur":4536,"pid":1,"tid":0,"args":["cached"]},
{"name":"scriptImportGraph","cat":"job","ph":"X","ts":95743904,"dur":3003,"pid":1,"tid":0,"args":["cached"]},
{"name":"methodCodeHashSignatures","cat":"job","ph":"X","ts":95747344,"dur":42303,"pid":1,"tid":0,"args":["cached"]}
]
